DataCleanerAI/__init__.py
DataCleanerAI/analyzer.py
DataCleanerAI/interact.py
DataCleanerAI/learn.py
DataCleanerAI-0.0.1.dist-info/LICENSE
DataCleanerAI-0.0.1.dist-info/METADATA
DataCleanerAI-0.0.1.dist-info/WHEEL
DataCleanerAI-0.0.1.dist-info/top_level.txt
DataCleanerAI-0.0.1.dist-info/RECORD
