Metadata-Version: 2.1
Name: DataCleanerAI
Version: 0.0.1
Summary: An interactive, intelligent data-cleaning library with ML-based user adaptation
Home-page: https://github.com/harshv-v/DataCleanerAI
Author: Harsha Vardhan
Author-email: harshav.vanukuri@gmail.com
License: MIT
Classifier: Programming Language :: Python :: 3
Classifier: License :: OSI Approved :: MIT License
Classifier: Operating System :: OS Independent
Requires-Python: >=3.6
License-File: LICENSE
Requires-Dist: pandas
Requires-Dist: numpy
Requires-Dist: scikit-learn
Requires-Dist: dask
Requires-Dist: matplotlib
Requires-Dist: spacy
